trytond/modules/account_primanota/README.rst
trytond/modules/account_primanota/__init__.py
trytond/modules/account_primanota/analytic.py
trytond/modules/account_primanota/analytic.xml
trytond/modules/account_primanota/menu.xml
trytond/modules/account_primanota/primanota.py
trytond/modules/account_primanota/primanota.xml
trytond/modules/account_primanota/tryton.cfg
trytond/modules/account_primanota/versiondep.txt
trytond/modules/account_primanota/locale/de.po
trytond/modules/account_primanota/locale/en.po
trytond/modules/account_primanota/tests/__init__.py
trytond/modules/account_primanota/tests/test_primanota.py
trytond/modules/account_primanota/view/analytic_form.xml
trytond/modules/account_primanota/view/analytic_list.xml
trytond/modules/account_primanota/view/analyticline_list.xml
trytond/modules/account_primanota/view/primanota_context_form.xml
trytond/modules/account_primanota/view/primanota_form.xml
trytond/modules/account_primanota/view/primanota_list.xml
trytond/modules/account_primanota/view/taxline_list.xml
mds_account_primanota-7.0.9.dist-info/LICENSE
mds_account_primanota-7.0.9.dist-info/METADATA
mds_account_primanota-7.0.9.dist-info/WHEEL
mds_account_primanota-7.0.9.dist-info/entry_points.txt
mds_account_primanota-7.0.9.dist-info/top_level.txt
mds_account_primanota-7.0.9.dist-info/RECORD
